MANIFEST.in
setup.cfg
setup.py
django_smart_autoregister/__init__.py
django_smart_autoregister/auto_register.py
django_smart_autoregister/django_admin_helper.py
django_smart_autoregister/django_helper.py
django_smart_autoregister/models.py
django_smart_autoregister/models_test.py
django_smart_autoregister.egg-info/PKG-INFO
django_smart_autoregister.egg-info/SOURCES.txt
django_smart_autoregister.egg-info/dependency_links.txt
django_smart_autoregister.egg-info/entry_points.txt
django_smart_autoregister.egg-info/requires.txt
django_smart_autoregister.egg-info/top_level.txt
django_smart_autoregister/tests/__init__.py
django_smart_autoregister/tests/test_dsa.py