Metadata-Version: 1.1
Name: django-smart-autoregister
Version: 0.0.1
Summary: Automatically register models in the admin interface in a smart way.
Home-page: https://github.com/paulocheque/django-smart-autoregister
Author: paulocheque
Author-email: paulocheque@gmail.com
License: MIT
Keywords: python django admin autoregister
Platform: UNKNOWN
Classifier: Framework :: Django
Classifier: Operating System :: OS Independent
Classifier: Topic :: Software Development
Classifier: Programming Language :: Python :: 2.7
Classifier: Programming Language :: Python :: 3.3
Classifier: Programming Language :: Python :: 3.4
Classifier: Programming Language :: Python :: Implementation :: PyPy
